.coveragerc
.gitignore
README.txt
bootstrap.py
buildout.cfg
jenkins
jenkins.bat
setup.py
tox.ini
checker/__init__.py
checker/version.txt
checker.egg-info/PKG-INFO
checker.egg-info/SOURCES.txt
checker.egg-info/dependency_links.txt
checker.egg-info/entry_points.txt
checker.egg-info/not-zip-safe
checker.egg-info/requires.txt
checker.egg-info/top_level.txt
checker/checkers/__init__.py
checker/checkers/buildout.py
checker/checkers/command.py
checker/checkers/crontab.py
checker/checkers/init.py
checker/checkers/jenkins.py
checker/checkers/os_packages.py
checker/checkers/path.py
checker/checkers/svn.py
checker/tests/__init__.py
checker/tests/base.py
checker/tests/test_buildout.py
checker/tests/test_crontab.py
checker/tests/test_docs.py
checker/tests/test_init.py
checker/tests/test_jenkins.py
checker/tests/test_main.py
checker/tests/test_os_packages.py
checker/tests/test_path.py
docs/Makefile
docs/changes.txt
docs/checkers.txt
docs/conf.py
docs/description.txt
docs/development.txt
docs/index.txt
docs/installation.txt
docs/license.txt
docs/make.bat
docs/use.txt