Metadata-Version: 1.0
Name: checker
Version: 1.6
Summary: A tool for checking system configuration.
Home-page: http://www.simplistix.co.uk/software/python/checker
Author: Chris Withers
Author-email: chris@simplistix.co.uk
License: MIT
Platform: UNKNOWN
Classifier: Development Status :: 5 - Production/Stable
Classifier: Intended Audience :: Developers
Classifier: License :: OSI Approved :: MIT License
